{
  "$schema": "http://cyclonedx.org/schema/bom-1.6.schema.json",
  "version": 1,
  "metadata": {
    "tools": [
      {
        "name": "trivy",
        "vendor": "aquasecurity",
        "version": "unknown"
      }
    ],
    "component": {
      "name": "python",
      "purl": "pkg:oci/python@3.9.5-slim-buster?digest=sha256:9828573e6a0b02b6d0ff0bae0716b027aa21cf8e59ac18a76724d216bab7ef04",
      "type": "library",
      "bom-ref": "pkg:oci/python@3.9.5-slim-buster?digest=sha256:9828573e6a0b02b6d0ff0bae0716b027aa21cf8e59ac18a76724d216bab7ef04",
      "version": "3.9.5-slim-buster"
    },
    "timestamp": "2024-10-21T19:28:18.126744+00:00"
  },
  "bomFormat": "CycloneDX",
  "components": [
    {
      "name": "adduser",
      "type": "library",
      "bom-ref": "BomRef.638522317601062.9061123453862939",
      "version": "3.118"
    },
    {
      "name": "apt",
      "type": "library",
      "bom-ref": "BomRef.6700044993875508.5892838828578716",
      "version": "1.8.2.3"
    },
    {
      "name": "base-files",
      "type": "library",
      "bom-ref": "BomRef.6494907790151351.618997674025335",
      "version": "10.3+deb10u10"
    },
    {
      "name": "base-passwd",
      "type": "library",
      "bom-ref": "BomRef.9442058484678021.3113516388955311",
      "version": "3.5.46"
    },
    {
      "name": "bash",
      "type": "library",
      "bom-ref": "BomRef.36606419643765153.5725618659469607",
      "version": "5.0-4"
    },
    {
      "name": "bsdutils",
      "type": "library",
      "bom-ref": "BomRef.8779491248235417.12421039780462917",
      "version": "1:2.33.1-0.1"
    },
    {
      "name": "c8f7e2a0-cdd4-43b2-a50d-0ab007284901",
      "type": "library",
      "bom-ref": "BomRef.4714792369182019.1162266721849895",
      "version": "unknown"
    },
    {
      "name": "ca-certificates",
      "type": "library",
      "bom-ref": "BomRef.3277733071009875.09831557579473871",
      "version": "20200601~deb10u2"
    },
    {
      "name": "coreutils",
      "type": "library",
      "bom-ref": "BomRef.3376297711206493.1957851498290788",
      "version": "8.30-3"
    },
    {
      "name": "dash",
      "type": "library",
      "bom-ref": "BomRef.3871849964276247.4893449023643319",
      "version": "0.5.10.2-5"
    },
    {
      "name": "debconf",
      "type": "library",
      "bom-ref": "BomRef.8226533638830004.4189804940221108",
      "version": "1.5.71"
    },
    {
      "name": "debian",
      "type": "library",
      "bom-ref": "BomRef.583307849103899.6550171492927704",
      "version": "10.10"
    },
    {
      "name": "debian-archive-keyring",
      "type": "library",
      "bom-ref": "BomRef.5928707323052028.14484117131808416",
      "version": "2019.1+deb10u1"
    },
    {
      "name": "debianutils",
      "type": "library",
      "bom-ref": "BomRef.13336875914912116.09440956437812198",
      "version": "4.8.6.1"
    },
    {
      "name": "diffutils",
      "type": "library",
      "bom-ref": "BomRef.17657866979526682.9814649883423175",
      "version": "1:3.7-3"
    },
    {
      "name": "dpkg",
      "type": "library",
      "bom-ref": "BomRef.09420498196233162.8372224100157705",
      "version": "1.19.7"
    },
    {
      "name": "e2fsprogs",
      "type": "library",
      "bom-ref": "BomRef.7681775543718559.16393058002058447",
      "version": "1.44.5-1+deb10u3"
    },
    {
      "name": "fdisk",
      "type": "library",
      "bom-ref": "BomRef.9078323994449894.9296705447335185",
      "version": "2.33.1-0.1"
    },
    {
      "name": "findutils",
      "type": "library",
      "bom-ref": "BomRef.2037223003609957.6990553858168258",
      "version": "4.6.0+git+20190209-2"
    },
    {
      "name": "gcc-8-base",
      "type": "library",
      "bom-ref": "BomRef.06152795812494294.3530021901379762",
      "version": "8.3.0-6"
    },
    {
      "name": "gpgv",
      "type": "library",
      "bom-ref": "BomRef.5888211273619267.970535791044228",
      "version": "2.2.12-1+deb10u1"
    },
    {
      "name": "grep",
      "type": "library",
      "bom-ref": "BomRef.18640961512670617.1278778571082515",
      "version": "3.3-1"
    },
    {
      "name": "gzip",
      "type": "library",
      "bom-ref": "BomRef.5220303030806162.2083981417408195",
      "version": "1.9-3"
    },
    {
      "name": "hostname",
      "type": "library",
      "bom-ref": "BomRef.8237258226930083.9508484751803226",
      "version": "3.21"
    },
    {
      "name": "init-system-helpers",
      "type": "library",
      "bom-ref": "BomRef.7794035926772811.77583095235425",
      "version": "1.56+nmu1"
    },
    {
      "name": "libacl1",
      "type": "library",
      "bom-ref": "BomRef.04429707805889771.016208775158520705",
      "version": "2.2.53-4"
    },
    {
      "name": "libapt-pkg5.0",
      "type": "library",
      "bom-ref": "BomRef.2726697936407906.5013737087868142",
      "version": "1.8.2.3"
    },
    {
      "name": "libattr1",
      "type": "library",
      "bom-ref": "BomRef.25984285851788336.8289933354882545",
      "version": "1:2.4.48-4"
    },
    {
      "name": "libaudit-common",
      "type": "library",
      "bom-ref": "BomRef.8932005643926842.22827573230885645",
      "version": "1:2.8.4-3"
    },
    {
      "name": "libaudit1",
      "type": "library",
      "bom-ref": "BomRef.06620151107547723.7973386516073198",
      "version": "1:2.8.4-3"
    },
    {
      "name": "libblkid1",
      "type": "library",
      "bom-ref": "BomRef.4448097219895859.8496550384548058",
      "version": "2.33.1-0.1"
    },
    {
      "name": "libbz2-1.0",
      "type": "library",
      "bom-ref": "BomRef.05342762155482039.37329605319193715",
      "version": "1.0.6-9.2~deb10u1"
    },
    {
      "name": "libc-bin",
      "type": "library",
      "bom-ref": "BomRef.624618319229353.8124543178739854",
      "version": "2.28-10"
    },
    {
      "name": "libc6",
      "type": "library",
      "bom-ref": "BomRef.014377694847221956.6006930728279941",
      "version": "2.28-10"
    },
    {
      "name": "libcap-ng0",
      "type": "library",
      "bom-ref": "BomRef.4060751102621204.583795329942096",
      "version": "0.7.9-2"
    },
    {
      "name": "libcom-err2",
      "type": "library",
      "bom-ref": "BomRef.05997547558444538.12285144681881877",
      "version": "1.44.5-1+deb10u3"
    },
    {
      "name": "libdb5.3",
      "type": "library",
      "bom-ref": "BomRef.306691233650479.3184914108745118",
      "version": "5.3.28+dfsg1-0.5"
    },
    {
      "name": "libdebconfclient0",
      "type": "library",
      "bom-ref": "BomRef.2117211778482564.31115486813573534",
      "version": "0.249"
    },
    {
      "name": "libexpat1",
      "type": "library",
      "bom-ref": "BomRef.5583486882302697.3879985401434414",
      "version": "2.2.6-2+deb10u1"
    },
    {
      "name": "libext2fs2",
      "type": "library",
      "bom-ref": "BomRef.8315727885006945.8894047277504243",
      "version": "1.44.5-1+deb10u3"
    },
    {
      "name": "libfdisk1",
      "type": "library",
      "bom-ref": "BomRef.9409551159293361.5854893937209357",
      "version": "2.33.1-0.1"
    },
    {
      "name": "libffi6",
      "type": "library",
      "bom-ref": "BomRef.9014272690494917.3168207067986012",
      "version": "3.2.1-9"
    },
    {
      "name": "libgcc1",
      "type": "library",
      "bom-ref": "BomRef.7265301443260351.4370412309715802",
      "version": "1:8.3.0-6"
    },
    {
      "name": "libgcrypt20",
      "type": "library",
      "bom-ref": "BomRef.12602792004093677.13898237844089922",
      "version": "1.8.4-5+deb10u1"
    },
    {
      "name": "libgdbm6",
      "type": "library",
      "bom-ref": "BomRef.9075719711185306.8652368580555755",
      "version": "1.18.1-4"
    },
    {
      "name": "libgmp10",
      "type": "library",
      "bom-ref": "BomRef.15769407493695542.7697437391105496",
      "version": "2:6.1.2+dfsg-4"
    },
    {
      "name": "libgnutls30",
      "type": "library",
      "bom-ref": "BomRef.6957230658729368.8357890071924468",
      "version": "3.6.7-4+deb10u7"
    },
    {
      "name": "libgpg-error0",
      "type": "library",
      "bom-ref": "BomRef.5803383305596549.48501789767915104",
      "version": "1.35-1"
    },
    {
      "name": "libhogweed4",
      "type": "library",
      "bom-ref": "BomRef.2101839051176141.9249530084755786",
      "version": "3.4.1-1+deb10u1"
    },
    {
      "name": "libidn2-0",
      "type": "library",
      "bom-ref": "BomRef.9725208628706689.9720108073682088",
      "version": "2.0.5-1+deb10u1"
    },
    {
      "name": "liblz4-1",
      "type": "library",
      "bom-ref": "BomRef.25673703221047217.8949899207239959",
      "version": "1.8.3-1+deb10u1"
    },
    {
      "name": "liblzma5",
      "type": "library",
      "bom-ref": "BomRef.6590625508715043.7509071665219865",
      "version": "5.2.4-1"
    },
    {
      "name": "libmount1",
      "type": "library",
      "bom-ref": "BomRef.5658740971019609.21739203843175525",
      "version": "2.33.1-0.1"
    },
    {
      "name": "libncursesw6",
      "type": "library",
      "bom-ref": "BomRef.44402926400307063.9214996031621715",
      "version": "6.1+20181013-2+deb10u2"
    },
    {
      "name": "libnettle6",
      "type": "library",
      "bom-ref": "BomRef.4010341759440781.35080000683900747",
      "version": "3.4.1-1+deb10u1"
    },
    {
      "name": "libp11-kit0",
      "type": "library",
      "bom-ref": "BomRef.3434052942822833.5397039381170327",
      "version": "0.23.15-2+deb10u1"
    },
    {
      "name": "libpam-modules",
      "type": "library",
      "bom-ref": "BomRef.33283971263764855.5367614665652368",
      "version": "1.3.1-5"
    },
    {
      "name": "libpam-modules-bin",
      "type": "library",
      "bom-ref": "BomRef.2068886767530287.18576227641838572",
      "version": "1.3.1-5"
    },
    {
      "name": "libpam-runtime",
      "type": "library",
      "bom-ref": "BomRef.5456486970552139.07243489245606194",
      "version": "1.3.1-5"
    },
    {
      "name": "libpam0g",
      "type": "library",
      "bom-ref": "BomRef.22578044736389835.6700805018025822",
      "version": "1.3.1-5"
    },
    {
      "name": "libpcre3",
      "type": "library",
      "bom-ref": "BomRef.6193300504397293.8720493839303153",
      "version": "2:8.39-12"
    },
    {
      "name": "libreadline7",
      "type": "library",
      "bom-ref": "BomRef.675441776271153.011605783395340574",
      "version": "7.0-5"
    },
    {
      "name": "libseccomp2",
      "type": "library",
      "bom-ref": "BomRef.8523739831321816.6836741628680265",
      "version": "2.3.3-4"
    },
    {
      "name": "libselinux1",
      "type": "library",
      "bom-ref": "BomRef.4161631654803263.29825156809142883",
      "version": "2.8-1+b1"
    },
    {
      "name": "libsemanage-common",
      "type": "library",
      "bom-ref": "BomRef.8085710535094197.5466021986175128",
      "version": "2.8-2"
    },
    {
      "name": "libsemanage1",
      "type": "library",
      "bom-ref": "BomRef.6411839628598913.5444423575645535",
      "version": "2.8-2"
    },
    {
      "name": "libsepol1",
      "type": "library",
      "bom-ref": "BomRef.22980697545990802.41712410354821017",
      "version": "2.8-1"
    },
    {
      "name": "libsmartcols1",
      "type": "library",
      "bom-ref": "BomRef.43967728134055784.14650436534685318",
      "version": "2.33.1-0.1"
    },
    {
      "name": "libsqlite3-0",
      "type": "library",
      "bom-ref": "BomRef.50751510255799.7625896369807257",
      "version": "3.27.2-3+deb10u1"
    },
    {
      "name": "libss2",
      "type": "library",
      "bom-ref": "BomRef.35664584826334045.6910816968511829",
      "version": "1.44.5-1+deb10u3"
    },
    {
      "name": "libssl1.1",
      "type": "library",
      "bom-ref": "BomRef.1584853772767587.2639328553311199",
      "version": "1.1.1d-0+deb10u6"
    },
    {
      "name": "libstdc++6",
      "type": "library",
      "bom-ref": "BomRef.4595584639544802.9904820822208436",
      "version": "8.3.0-6"
    },
    {
      "name": "libsystemd0",
      "type": "library",
      "bom-ref": "BomRef.18337437700980785.7548085589791259",
      "version": "241-7~deb10u7"
    },
    {
      "name": "libtasn1-6",
      "type": "library",
      "bom-ref": "BomRef.4895747623805745.028093013759035723",
      "version": "4.13-3"
    },
    {
      "name": "libtinfo6",
      "type": "library",
      "bom-ref": "BomRef.7462134380267184.8633571336649027",
      "version": "6.1+20181013-2+deb10u2"
    },
    {
      "name": "libudev1",
      "type": "library",
      "bom-ref": "BomRef.06350124807521984.789584264917086",
      "version": "241-7~deb10u7"
    },
    {
      "name": "libunistring2",
      "type": "library",
      "bom-ref": "BomRef.741369701796967.8024497457299178",
      "version": "0.9.10-1"
    },
    {
      "name": "libuuid1",
      "type": "library",
      "bom-ref": "BomRef.8356017327909376.6803241166279047",
      "version": "2.33.1-0.1"
    },
    {
      "name": "libzstd1",
      "type": "library",
      "bom-ref": "BomRef.9505408335772655.24691552266085004",
      "version": "1.3.8+dfsg-3+deb10u2"
    },
    {
      "name": "login",
      "type": "library",
      "bom-ref": "BomRef.20141590629089534.8561055338559156",
      "version": "1:4.5-1.1"
    },
    {
      "name": "mawk",
      "type": "library",
      "bom-ref": "BomRef.8207235311155777.8406082287804161",
      "version": "1.3.3-17+b3"
    },
    {
      "name": "mount",
      "type": "library",
      "bom-ref": "BomRef.692861547795587.9359387350244609",
      "version": "2.33.1-0.1"
    },
    {
      "name": "ncurses-base",
      "type": "library",
      "bom-ref": "BomRef.3885142529558141.7687475348635976",
      "version": "6.1+20181013-2+deb10u2"
    },
    {
      "name": "ncurses-bin",
      "type": "library",
      "bom-ref": "BomRef.248725237297323.034596145334793604",
      "version": "6.1+20181013-2+deb10u2"
    },
    {
      "name": "netbase",
      "type": "library",
      "bom-ref": "BomRef.7877324857815516.31843835605556436",
      "version": "5.6"
    },
    {
      "name": "openssl",
      "type": "library",
      "bom-ref": "BomRef.29042988215637777.9469224760131464",
      "version": "1.1.1d-0+deb10u6"
    },
    {
      "name": "passwd",
      "type": "library",
      "bom-ref": "BomRef.04806015559114185.8129755548264647",
      "version": "1:4.5-1.1"
    },
    {
      "name": "perl-base",
      "type": "library",
      "bom-ref": "BomRef.16132078460116073.5887932322723473",
      "version": "5.28.1-6+deb10u1"
    },
    {
      "name": "pip",
      "type": "library",
      "bom-ref": "BomRef.09951863787762782.4208514726929774",
      "version": "21.1.3"
    },
    {
      "name": "pkg:deb/debian/adduser@3.118?arch=all&distro=debian-10.10",
      "type": "library",
      "bom-ref": "BomRef.20004265412418543.14515752786210412",
      "version": "unknown"
    },
    {
      "name": "pkg:deb/debian/apt@1.8.2.3?arch=amd64&distro=debian-10.10",
      "type": "library",
      "bom-ref": "BomRef.5717771222802057.2843713902479015",
      "version": "unknown"
    },
    {
      "name": "pkg:deb/debian/base-files@10.3%2Bdeb10u10?arch=amd64&distro=debian-10.10",
      "type": "library",
      "bom-ref": "BomRef.3348688085990237.3839060809638948",
      "version": "unknown"
    },
    {
      "name": "pkg:deb/debian/base-passwd@3.5.46?arch=amd64&distro=debian-10.10",
      "type": "library",
      "bom-ref": "BomRef.0095309809089823.5072495081008317",
      "version": "unknown"
    },
    {
      "name": "pkg:deb/debian/bash@5.0-4?arch=amd64&distro=debian-10.10",
      "type": "library",
      "bom-ref": "BomRef.9141330146957267.10393444987624467",
      "version": "unknown"
    },
    {
      "name": "pkg:deb/debian/bsdutils@2.33.1-0.1?arch=amd64&distro=debian-10.10&epoch=1",
      "type": "library",
      "bom-ref": "BomRef.040123132165701736.8070528428543325",
      "version": "unknown"
    },
    {
      "name": "pkg:deb/debian/ca-certificates@20200601~deb10u2?arch=all&distro=debian-10.10",
      "type": "library",
      "bom-ref": "BomRef.7081291679447421.6095609737199661",
      "version": "unknown"
    },
    {
      "name": "pkg:deb/debian/coreutils@8.30-3?arch=amd64&distro=debian-10.10",
      "type": "library",
      "bom-ref": "BomRef.7863311014160747.1676416986153968",
      "version": "unknown"
    },
    {
      "name": "pkg:deb/debian/dash@0.5.10.2-5?arch=amd64&distro=debian-10.10",
      "type": "library",
      "bom-ref": "BomRef.8724476333438951.5957306897205458",
      "version": "unknown"
    },
    {
      "name": "pkg:deb/debian/debconf@1.5.71?arch=all&distro=debian-10.10",
      "type": "library",
      "bom-ref": "BomRef.9404764452674748.466210018422351",
      "version": "unknown"
    },
    {
      "name": "pkg:deb/debian/debian-archive-keyring@2019.1%2Bdeb10u1?arch=all&distro=debian-10.10",
      "type": "library",
      "bom-ref": "BomRef.7323940112021076.19460701179761497",
      "version": "unknown"
    },
    {
      "name": "pkg:deb/debian/debianutils@4.8.6.1?arch=amd64&distro=debian-10.10",
      "type": "library",
      "bom-ref": "BomRef.6417393249903256.18941865886318765",
      "version": "unknown"
    },
    {
      "name": "pkg:deb/debian/diffutils@3.7-3?arch=amd64&distro=debian-10.10&epoch=1",
      "type": "library",
      "bom-ref": "BomRef.8971866655370766.6767660145496808",
      "version": "unknown"
    },
    {
      "name": "pkg:deb/debian/dpkg@1.19.7?arch=amd64&distro=debian-10.10",
      "type": "library",
      "bom-ref": "BomRef.8717348879909673.13562669835811614",
      "version": "unknown"
    },
    {
      "name": "pkg:deb/debian/e2fsprogs@1.44.5-1%2Bdeb10u3?arch=amd64&distro=debian-10.10",
      "type": "library",
      "bom-ref": "BomRef.9390377813408393.6257444931680743",
      "version": "unknown"
    },
    {
      "name": "pkg:deb/debian/fdisk@2.33.1-0.1?arch=amd64&distro=debian-10.10",
      "type": "library",
      "bom-ref": "BomRef.6251930966846826.25512310681413275",
      "version": "unknown"
    },
    {
      "name": "pkg:deb/debian/findutils@4.6.0%2Bgit%2B20190209-2?arch=amd64&distro=debian-10.10",
      "type": "library",
      "bom-ref": "BomRef.14451475064491726.34523007342203793",
      "version": "unknown"
    },
    {
      "name": "pkg:deb/debian/gcc-8-base@8.3.0-6?arch=amd64&distro=debian-10.10",
      "type": "library",
      "bom-ref": "BomRef.012535361945590129.9122748973520791",
      "version": "unknown"
    },
    {
      "name": "pkg:deb/debian/gpgv@2.2.12-1%2Bdeb10u1?arch=amd64&distro=debian-10.10",
      "type": "library",
      "bom-ref": "BomRef.0874616762963647.42994942210858644",
      "version": "unknown"
    },
    {
      "name": "pkg:deb/debian/grep@3.3-1?arch=amd64&distro=debian-10.10",
      "type": "library",
      "bom-ref": "BomRef.708455655678697.5211974773023408",
      "version": "unknown"
    },
    {
      "name": "pkg:deb/debian/gzip@1.9-3?arch=amd64&distro=debian-10.10",
      "type": "library",
      "bom-ref": "BomRef.19532797666570256.9508458421329402",
      "version": "unknown"
    },
    {
      "name": "pkg:deb/debian/hostname@3.21?arch=amd64&distro=debian-10.10",
      "type": "library",
      "bom-ref": "BomRef.8554812557254269.8811462143957093",
      "version": "unknown"
    },
    {
      "name": "pkg:deb/debian/init-system-helpers@1.56%2Bnmu1?arch=all&distro=debian-10.10",
      "type": "library",
      "bom-ref": "BomRef.14147180061391673.8962006856993706",
      "version": "unknown"
    },
    {
      "name": "pkg:deb/debian/libacl1@2.2.53-4?arch=amd64&distro=debian-10.10",
      "type": "library",
      "bom-ref": "BomRef.44922926910712924.8555338650751567",
      "version": "unknown"
    },
    {
      "name": "pkg:deb/debian/libapt-pkg5.0@1.8.2.3?arch=amd64&distro=debian-10.10",
      "type": "library",
      "bom-ref": "BomRef.349679833039911.4594572055190672",
      "version": "unknown"
    },
    {
      "name": "pkg:deb/debian/libattr1@2.4.48-4?arch=amd64&distro=debian-10.10&epoch=1",
      "type": "library",
      "bom-ref": "BomRef.15085771322295782.8436751606754916",
      "version": "unknown"
    },
    {
      "name": "pkg:deb/debian/libaudit-common@2.8.4-3?arch=all&distro=debian-10.10&epoch=1",
      "type": "library",
      "bom-ref": "BomRef.8278158252697938.1525089175639801",
      "version": "unknown"
    },
    {
      "name": "pkg:deb/debian/libaudit1@2.8.4-3?arch=amd64&distro=debian-10.10&epoch=1",
      "type": "library",
      "bom-ref": "BomRef.28913774963615935.3175846434973876",
      "version": "unknown"
    },
    {
      "name": "pkg:deb/debian/libblkid1@2.33.1-0.1?arch=amd64&distro=debian-10.10",
      "type": "library",
      "bom-ref": "BomRef.10186921736217669.8758035825460015",
      "version": "unknown"
    },
    {
      "name": "pkg:deb/debian/libbz2-1.0@1.0.6-9.2~deb10u1?arch=amd64&distro=debian-10.10",
      "type": "library",
      "bom-ref": "BomRef.7366352057467452.7322840389013792",
      "version": "unknown"
    },
    {
      "name": "pkg:deb/debian/libc-bin@2.28-10?arch=amd64&distro=debian-10.10",
      "type": "library",
      "bom-ref": "BomRef.5531971328695336.8132835120680112",
      "version": "unknown"
    },
    {
      "name": "pkg:deb/debian/libc6@2.28-10?arch=amd64&distro=debian-10.10",
      "type": "library",
      "bom-ref": "BomRef.3156146626796813.6284868379111672",
      "version": "unknown"
    },
    {
      "name": "pkg:deb/debian/libcap-ng0@0.7.9-2?arch=amd64&distro=debian-10.10",
      "type": "library",
      "bom-ref": "BomRef.4362608078426272.7715125331972799",
      "version": "unknown"
    },
    {
      "name": "pkg:deb/debian/libcom-err2@1.44.5-1%2Bdeb10u3?arch=amd64&distro=debian-10.10",
      "type": "library",
      "bom-ref": "BomRef.08459043109156994.9376935757832566",
      "version": "unknown"
    },
    {
      "name": "pkg:deb/debian/libdb5.3@5.3.28%2Bdfsg1-0.5?arch=amd64&distro=debian-10.10",
      "type": "library",
      "bom-ref": "BomRef.39399536755445586.9034341664356975",
      "version": "unknown"
    },
    {
      "name": "pkg:deb/debian/libdebconfclient0@0.249?arch=amd64&distro=debian-10.10",
      "type": "library",
      "bom-ref": "BomRef.9900452577318635.8204726322689062",
      "version": "unknown"
    },
    {
      "name": "pkg:deb/debian/libexpat1@2.2.6-2%2Bdeb10u1?arch=amd64&distro=debian-10.10",
      "type": "library",
      "bom-ref": "BomRef.5104747997287611.18798433681584203",
      "version": "unknown"
    },
    {
      "name": "pkg:deb/debian/libext2fs2@1.44.5-1%2Bdeb10u3?arch=amd64&distro=debian-10.10",
      "type": "library",
      "bom-ref": "BomRef.9806212688129069.7401904180658876",
      "version": "unknown"
    },
    {
      "name": "pkg:deb/debian/libfdisk1@2.33.1-0.1?arch=amd64&distro=debian-10.10",
      "type": "library",
      "bom-ref": "BomRef.18214832576681317.7070043038742426",
      "version": "unknown"
    },
    {
      "name": "pkg:deb/debian/libffi6@3.2.1-9?arch=amd64&distro=debian-10.10",
      "type": "library",
      "bom-ref": "BomRef.3935203661690767.008572202136490348",
      "version": "unknown"
    },
    {
      "name": "pkg:deb/debian/libgcc1@8.3.0-6?arch=amd64&distro=debian-10.10&epoch=1",
      "type": "library",
      "bom-ref": "BomRef.949577046776123.3870562633565051",
      "version": "unknown"
    },
    {
      "name": "pkg:deb/debian/libgcrypt20@1.8.4-5%2Bdeb10u1?arch=amd64&distro=debian-10.10",
      "type": "library",
      "bom-ref": "BomRef.6227516847696897.34184629283261014",
      "version": "unknown"
    },
    {
      "name": "pkg:deb/debian/libgdbm6@1.18.1-4?arch=amd64&distro=debian-10.10",
      "type": "library",
      "bom-ref": "BomRef.22160974381192233.95078512074112",
      "version": "unknown"
    },
    {
      "name": "pkg:deb/debian/libgmp10@6.1.2%2Bdfsg-4?arch=amd64&distro=debian-10.10&epoch=2",
      "type": "library",
      "bom-ref": "BomRef.8927768714316229.19303063943966947",
      "version": "unknown"
    },
    {
      "name": "pkg:deb/debian/libgnutls30@3.6.7-4%2Bdeb10u7?arch=amd64&distro=debian-10.10",
      "type": "library",
      "bom-ref": "BomRef.5507000523602356.17989846013187527",
      "version": "unknown"
    },
    {
      "name": "pkg:deb/debian/libgpg-error0@1.35-1?arch=amd64&distro=debian-10.10",
      "type": "library",
      "bom-ref": "BomRef.0031990986119523335.13419301659285665",
      "version": "unknown"
    },
    {
      "name": "pkg:deb/debian/libhogweed4@3.4.1-1%2Bdeb10u1?arch=amd64&distro=debian-10.10",
      "type": "library",
      "bom-ref": "BomRef.04873405550707588.5146986046532009",
      "version": "unknown"
    },
    {
      "name": "pkg:deb/debian/libidn2-0@2.0.5-1%2Bdeb10u1?arch=amd64&distro=debian-10.10",
      "type": "library",
      "bom-ref": "BomRef.12215021548904725.07399066514210295",
      "version": "unknown"
    },
    {
      "name": "pkg:deb/debian/liblz4-1@1.8.3-1%2Bdeb10u1?arch=amd64&distro=debian-10.10",
      "type": "library",
      "bom-ref": "BomRef.2474886628520887.9444601956018153",
      "version": "unknown"
    },
    {
      "name": "pkg:deb/debian/liblzma5@5.2.4-1?arch=amd64&distro=debian-10.10",
      "type": "library",
      "bom-ref": "BomRef.081780575936241.532895358768341",
      "version": "unknown"
    },
    {
      "name": "pkg:deb/debian/libmount1@2.33.1-0.1?arch=amd64&distro=debian-10.10",
      "type": "library",
      "bom-ref": "BomRef.2749070365904026.13946846464047624",
      "version": "unknown"
    },
    {
      "name": "pkg:deb/debian/libncursesw6@6.1%2B20181013-2%2Bdeb10u2?arch=amd64&distro=debian-10.10",
      "type": "library",
      "bom-ref": "BomRef.11645890342214582.9519048146160358",
      "version": "unknown"
    },
    {
      "name": "pkg:deb/debian/libnettle6@3.4.1-1%2Bdeb10u1?arch=amd64&distro=debian-10.10",
      "type": "library",
      "bom-ref": "BomRef.9906411226171477.7059222856741965",
      "version": "unknown"
    },
    {
      "name": "pkg:deb/debian/libp11-kit0@0.23.15-2%2Bdeb10u1?arch=amd64&distro=debian-10.10",
      "type": "library",
      "bom-ref": "BomRef.9708420420437847.39566352630348745",
      "version": "unknown"
    },
    {
      "name": "pkg:deb/debian/libpam-modules-bin@1.3.1-5?arch=amd64&distro=debian-10.10",
      "type": "library",
      "bom-ref": "BomRef.7484559196627131.3643589839021296",
      "version": "unknown"
    },
    {
      "name": "pkg:deb/debian/libpam-modules@1.3.1-5?arch=amd64&distro=debian-10.10",
      "type": "library",
      "bom-ref": "BomRef.9261053826445684.5120762659737454",
      "version": "unknown"
    },
    {
      "name": "pkg:deb/debian/libpam-runtime@1.3.1-5?arch=all&distro=debian-10.10",
      "type": "library",
      "bom-ref": "BomRef.42945543822967414.48162972174599994",
      "version": "unknown"
    },
    {
      "name": "pkg:deb/debian/libpam0g@1.3.1-5?arch=amd64&distro=debian-10.10",
      "type": "library",
      "bom-ref": "BomRef.7408051170405284.7916020144210236",
      "version": "unknown"
    },
    {
      "name": "pkg:deb/debian/libpcre3@8.39-12?arch=amd64&distro=debian-10.10&epoch=2",
      "type": "library",
      "bom-ref": "BomRef.44959855469721843.9908295921008714",
      "version": "unknown"
    },
    {
      "name": "pkg:deb/debian/libreadline7@7.0-5?arch=amd64&distro=debian-10.10",
      "type": "library",
      "bom-ref": "BomRef.5627778898350738.61190172072563",
      "version": "unknown"
    },
    {
      "name": "pkg:deb/debian/libseccomp2@2.3.3-4?arch=amd64&distro=debian-10.10",
      "type": "library",
      "bom-ref": "BomRef.06416709962005096.4888970081660051",
      "version": "unknown"
    },
    {
      "name": "pkg:deb/debian/libselinux1@2.8-1%2Bb1?arch=amd64&distro=debian-10.10",
      "type": "library",
      "bom-ref": "BomRef.8251538260144693.40855689882664714",
      "version": "unknown"
    },
    {
      "name": "pkg:deb/debian/libsemanage-common@2.8-2?arch=all&distro=debian-10.10",
      "type": "library",
      "bom-ref": "BomRef.2844614411670586.669310291046318",
      "version": "unknown"
    },
    {
      "name": "pkg:deb/debian/libsemanage1@2.8-2?arch=amd64&distro=debian-10.10",
      "type": "library",
      "bom-ref": "BomRef.7607252862441551.8563549855483767",
      "version": "unknown"
    },
    {
      "name": "pkg:deb/debian/libsepol1@2.8-1?arch=amd64&distro=debian-10.10",
      "type": "library",
      "bom-ref": "BomRef.5387680828856152.6388385686537119",
      "version": "unknown"
    },
    {
      "name": "pkg:deb/debian/libsmartcols1@2.33.1-0.1?arch=amd64&distro=debian-10.10",
      "type": "library",
      "bom-ref": "BomRef.23377253184068147.27898549050942245",
      "version": "unknown"
    },
    {
      "name": "pkg:deb/debian/libsqlite3-0@3.27.2-3%2Bdeb10u1?arch=amd64&distro=debian-10.10",
      "type": "library",
      "bom-ref": "BomRef.222876397243708.9027075281271735",
      "version": "unknown"
    },
    {
      "name": "pkg:deb/debian/libss2@1.44.5-1%2Bdeb10u3?arch=amd64&distro=debian-10.10",
      "type": "library",
      "bom-ref": "BomRef.22383416390356636.5631032528394329",
      "version": "unknown"
    },
    {
      "name": "pkg:deb/debian/libssl1.1@1.1.1d-0%2Bdeb10u6?arch=amd64&distro=debian-10.10",
      "type": "library",
      "bom-ref": "BomRef.4168815025116518.6817333439662973",
      "version": "unknown"
    },
    {
      "name": "pkg:deb/debian/libstdc%2B%2B6@8.3.0-6?arch=amd64&distro=debian-10.10",
      "type": "library",
      "bom-ref": "BomRef.032198773959995486.8989407618545395",
      "version": "unknown"
    },
    {
      "name": "pkg:deb/debian/libsystemd0@241-7~deb10u7?arch=amd64&distro=debian-10.10",
      "type": "library",
      "bom-ref": "BomRef.8420249951333507.45021286727235166",
      "version": "unknown"
    },
    {
      "name": "pkg:deb/debian/libtasn1-6@4.13-3?arch=amd64&distro=debian-10.10",
      "type": "library",
      "bom-ref": "BomRef.09529621393739218.7696974211565076",
      "version": "unknown"
    },
    {
      "name": "pkg:deb/debian/libtinfo6@6.1%2B20181013-2%2Bdeb10u2?arch=amd64&distro=debian-10.10",
      "type": "library",
      "bom-ref": "BomRef.751515612825079.651987136690016",
      "version": "unknown"
    },
    {
      "name": "pkg:deb/debian/libudev1@241-7~deb10u7?arch=amd64&distro=debian-10.10",
      "type": "library",
      "bom-ref": "BomRef.750698910333849.6128134415094723",
      "version": "unknown"
    },
    {
      "name": "pkg:deb/debian/libunistring2@0.9.10-1?arch=amd64&distro=debian-10.10",
      "type": "library",
      "bom-ref": "BomRef.22387850531904407.8687980489040354",
      "version": "unknown"
    },
    {
      "name": "pkg:deb/debian/libuuid1@2.33.1-0.1?arch=amd64&distro=debian-10.10",
      "type": "library",
      "bom-ref": "BomRef.3980472737203915.6651743917413009",
      "version": "unknown"
    },
    {
      "name": "pkg:deb/debian/libzstd1@1.3.8%2Bdfsg-3%2Bdeb10u2?arch=amd64&distro=debian-10.10",
      "type": "library",
      "bom-ref": "BomRef.5208843213527907.393955509910922",
      "version": "unknown"
    },
    {
      "name": "pkg:deb/debian/login@4.5-1.1?arch=amd64&distro=debian-10.10&epoch=1",
      "type": "library",
      "bom-ref": "BomRef.9324019542728219.3804584541406033",
      "version": "unknown"
    },
    {
      "name": "pkg:deb/debian/mawk@1.3.3-17%2Bb3?arch=amd64&distro=debian-10.10",
      "type": "library",
      "bom-ref": "BomRef.9679682594062538.4576567344035114",
      "version": "unknown"
    },
    {
      "name": "pkg:deb/debian/mount@2.33.1-0.1?arch=amd64&distro=debian-10.10",
      "type": "library",
      "bom-ref": "BomRef.9642927014015983.7011839252366258",
      "version": "unknown"
    },
    {
      "name": "pkg:deb/debian/ncurses-base@6.1%2B20181013-2%2Bdeb10u2?arch=all&distro=debian-10.10",
      "type": "library",
      "bom-ref": "BomRef.8600948291765768.09410291332060183",
      "version": "unknown"
    },
    {
      "name": "pkg:deb/debian/ncurses-bin@6.1%2B20181013-2%2Bdeb10u2?arch=amd64&distro=debian-10.10",
      "type": "library",
      "bom-ref": "BomRef.41873196607327745.7779813290235048",
      "version": "unknown"
    },
    {
      "name": "pkg:deb/debian/netbase@5.6?arch=all&distro=debian-10.10",
      "type": "library",
      "bom-ref": "BomRef.6389616729111299.048858513373669754",
      "version": "unknown"
    },
    {
      "name": "pkg:deb/debian/openssl@1.1.1d-0%2Bdeb10u6?arch=amd64&distro=debian-10.10",
      "type": "library",
      "bom-ref": "BomRef.10711624376149476.30378971532914156",
      "version": "unknown"
    },
    {
      "name": "pkg:deb/debian/passwd@4.5-1.1?arch=amd64&distro=debian-10.10&epoch=1",
      "type": "library",
      "bom-ref": "BomRef.5512700229642611.49067910431239703",
      "version": "unknown"
    },
    {
      "name": "pkg:deb/debian/perl-base@5.28.1-6%2Bdeb10u1?arch=amd64&distro=debian-10.10",
      "type": "library",
      "bom-ref": "BomRef.6256210560287165.3450624851081855",
      "version": "unknown"
    },
    {
      "name": "pkg:deb/debian/readline-common@7.0-5?arch=all&distro=debian-10.10",
      "type": "library",
      "bom-ref": "BomRef.37567027292248745.07581268429359755",
      "version": "unknown"
    },
    {
      "name": "pkg:deb/debian/sed@4.7-1?arch=amd64&distro=debian-10.10",
      "type": "library",
      "bom-ref": "BomRef.5915165309850273.2542605602452721",
      "version": "unknown"
    },
    {
      "name": "pkg:deb/debian/sysvinit-utils@2.93-8?arch=amd64&distro=debian-10.10",
      "type": "library",
      "bom-ref": "BomRef.7467081247267268.7978240810192762",
      "version": "unknown"
    },
    {
      "name": "pkg:deb/debian/tar@1.30%2Bdfsg-6?arch=amd64&distro=debian-10.10",
      "type": "library",
      "bom-ref": "BomRef.61182297178703.6175824292461738",
      "version": "unknown"
    },
    {
      "name": "pkg:deb/debian/tzdata@2021a-0%2Bdeb10u1?arch=all&distro=debian-10.10",
      "type": "library",
      "bom-ref": "BomRef.1369785486965518.28441016646890105",
      "version": "unknown"
    },
    {
      "name": "pkg:deb/debian/util-linux@2.33.1-0.1?arch=amd64&distro=debian-10.10",
      "type": "library",
      "bom-ref": "BomRef.026813700702035703.5637518522889091",
      "version": "unknown"
    },
    {
      "name": "pkg:deb/debian/zlib1g@1.2.11.dfsg-1?arch=amd64&distro=debian-10.10&epoch=1",
      "type": "library",
      "bom-ref": "BomRef.9486407515737253.8234470063246012",
      "version": "unknown"
    },
    {
      "name": "pkg:oci/python@sha256%3A9828573e6a0b02b6d0ff0bae0716b027aa21cf8e59ac18a76724d216bab7ef04?arch=amd64&repository_url=index.docker.io%2Flibrary%2Fpython",
      "type": "library",
      "bom-ref": "BomRef.6749908958490989.4774595140502519",
      "version": "unknown"
    },
    {
      "name": "pkg:pypi/pip@21.1.3",
      "type": "library",
      "bom-ref": "BomRef.29486081123640495.8734124170706987",
      "version": "unknown"
    },
    {
      "name": "pkg:pypi/setuptools@57.0.0",
      "type": "library",
      "bom-ref": "BomRef.396459539093175.05943967304401554",
      "version": "unknown"
    },
    {
      "name": "pkg:pypi/wheel@0.36.2",
      "type": "library",
      "bom-ref": "BomRef.1976420789654333.25486462891536177",
      "version": "unknown"
    },
    {
      "name": "readline-common",
      "type": "library",
      "bom-ref": "BomRef.8321758074155976.22215579648293882",
      "version": "7.0-5"
    },
    {
      "name": "sed",
      "type": "library",
      "bom-ref": "BomRef.5312832201840979.22563344220106119",
      "version": "4.7-1"
    },
    {
      "name": "setuptools",
      "type": "library",
      "bom-ref": "BomRef.6666388659586958.6253996220042775",
      "version": "57.0.0"
    },
    {
      "name": "sysvinit-utils",
      "type": "library",
      "bom-ref": "BomRef.8972279932670203.8215087135611291",
      "version": "2.93-8"
    },
    {
      "name": "tar",
      "type": "library",
      "bom-ref": "BomRef.5496756500684283.6776621350400049",
      "version": "1.30+dfsg-6"
    },
    {
      "name": "tzdata",
      "type": "library",
      "bom-ref": "BomRef.088437751651807.6453192725102423",
      "version": "2021a-0+deb10u1"
    },
    {
      "name": "util-linux",
      "type": "library",
      "bom-ref": "BomRef.11875097979392712.5020150830897288",
      "version": "2.33.1-0.1"
    },
    {
      "name": "wheel",
      "type": "library",
      "bom-ref": "BomRef.058780144264163114.18604916805807525",
      "version": "0.36.2"
    },
    {
      "name": "zlib1g",
      "type": "library",
      "bom-ref": "BomRef.8600934580652352.7275699295992998",
      "version": "1:1.2.11.dfsg-1"
    }
  ],
  "specVersion": "1.6",
  "dependencies": [
    {
      "ref": "BomRef.4714792369182019.1162266721849895"
    },
    {
      "ref": "BomRef.20004265412418543.14515752786210412"
    },
    {
      "ref": "BomRef.5717771222802057.2843713902479015"
    },
    {
      "ref": "BomRef.3348688085990237.3839060809638948"
    },
    {
      "ref": "BomRef.0095309809089823.5072495081008317"
    },
    {
      "ref": "BomRef.9141330146957267.10393444987624467"
    },
    {
      "ref": "BomRef.040123132165701736.8070528428543325"
    },
    {
      "ref": "BomRef.7081291679447421.6095609737199661"
    },
    {
      "ref": "BomRef.7863311014160747.1676416986153968"
    },
    {
      "ref": "BomRef.8724476333438951.5957306897205458"
    },
    {
      "ref": "BomRef.9404764452674748.466210018422351"
    },
    {
      "ref": "BomRef.7323940112021076.19460701179761497"
    },
    {
      "ref": "BomRef.6417393249903256.18941865886318765"
    },
    {
      "ref": "BomRef.8971866655370766.6767660145496808"
    },
    {
      "ref": "BomRef.8717348879909673.13562669835811614"
    },
    {
      "ref": "BomRef.9390377813408393.6257444931680743"
    },
    {
      "ref": "BomRef.6251930966846826.25512310681413275"
    },
    {
      "ref": "BomRef.14451475064491726.34523007342203793"
    },
    {
      "ref": "BomRef.012535361945590129.9122748973520791"
    },
    {
      "ref": "BomRef.0874616762963647.42994942210858644"
    },
    {
      "ref": "BomRef.708455655678697.5211974773023408"
    },
    {
      "ref": "BomRef.19532797666570256.9508458421329402"
    },
    {
      "ref": "BomRef.8554812557254269.8811462143957093"
    },
    {
      "ref": "BomRef.14147180061391673.8962006856993706"
    },
    {
      "ref": "BomRef.44922926910712924.8555338650751567"
    },
    {
      "ref": "BomRef.349679833039911.4594572055190672"
    },
    {
      "ref": "BomRef.15085771322295782.8436751606754916"
    },
    {
      "ref": "BomRef.8278158252697938.1525089175639801"
    },
    {
      "ref": "BomRef.28913774963615935.3175846434973876"
    },
    {
      "ref": "BomRef.10186921736217669.8758035825460015"
    },
    {
      "ref": "BomRef.7366352057467452.7322840389013792"
    },
    {
      "ref": "BomRef.5531971328695336.8132835120680112"
    },
    {
      "ref": "BomRef.3156146626796813.6284868379111672"
    },
    {
      "ref": "BomRef.4362608078426272.7715125331972799"
    },
    {
      "ref": "BomRef.08459043109156994.9376935757832566"
    },
    {
      "ref": "BomRef.39399536755445586.9034341664356975"
    },
    {
      "ref": "BomRef.9900452577318635.8204726322689062"
    },
    {
      "ref": "BomRef.5104747997287611.18798433681584203"
    },
    {
      "ref": "BomRef.9806212688129069.7401904180658876"
    },
    {
      "ref": "BomRef.18214832576681317.7070043038742426"
    },
    {
      "ref": "BomRef.3935203661690767.008572202136490348"
    },
    {
      "ref": "BomRef.949577046776123.3870562633565051"
    },
    {
      "ref": "BomRef.6227516847696897.34184629283261014"
    },
    {
      "ref": "BomRef.22160974381192233.95078512074112"
    },
    {
      "ref": "BomRef.8927768714316229.19303063943966947"
    },
    {
      "ref": "BomRef.5507000523602356.17989846013187527"
    },
    {
      "ref": "BomRef.0031990986119523335.13419301659285665"
    },
    {
      "ref": "BomRef.04873405550707588.5146986046532009"
    },
    {
      "ref": "BomRef.12215021548904725.07399066514210295"
    },
    {
      "ref": "BomRef.2474886628520887.9444601956018153"
    },
    {
      "ref": "BomRef.081780575936241.532895358768341"
    },
    {
      "ref": "BomRef.2749070365904026.13946846464047624"
    },
    {
      "ref": "BomRef.11645890342214582.9519048146160358"
    },
    {
      "ref": "BomRef.9906411226171477.7059222856741965"
    },
    {
      "ref": "BomRef.9708420420437847.39566352630348745"
    },
    {
      "ref": "BomRef.7484559196627131.3643589839021296"
    },
    {
      "ref": "BomRef.9261053826445684.5120762659737454"
    },
    {
      "ref": "BomRef.42945543822967414.48162972174599994"
    },
    {
      "ref": "BomRef.7408051170405284.7916020144210236"
    },
    {
      "ref": "BomRef.44959855469721843.9908295921008714"
    },
    {
      "ref": "BomRef.5627778898350738.61190172072563"
    },
    {
      "ref": "BomRef.06416709962005096.4888970081660051"
    },
    {
      "ref": "BomRef.8251538260144693.40855689882664714"
    },
    {
      "ref": "BomRef.2844614411670586.669310291046318"
    },
    {
      "ref": "BomRef.7607252862441551.8563549855483767"
    },
    {
      "ref": "BomRef.5387680828856152.6388385686537119"
    },
    {
      "ref": "BomRef.23377253184068147.27898549050942245"
    },
    {
      "ref": "BomRef.222876397243708.9027075281271735"
    },
    {
      "ref": "BomRef.22383416390356636.5631032528394329"
    },
    {
      "ref": "BomRef.4168815025116518.6817333439662973"
    },
    {
      "ref": "BomRef.032198773959995486.8989407618545395"
    },
    {
      "ref": "BomRef.8420249951333507.45021286727235166"
    },
    {
      "ref": "BomRef.09529621393739218.7696974211565076"
    },
    {
      "ref": "BomRef.751515612825079.651987136690016"
    },
    {
      "ref": "BomRef.750698910333849.6128134415094723"
    },
    {
      "ref": "BomRef.22387850531904407.8687980489040354"
    },
    {
      "ref": "BomRef.3980472737203915.6651743917413009"
    },
    {
      "ref": "BomRef.5208843213527907.393955509910922"
    },
    {
      "ref": "BomRef.9324019542728219.3804584541406033"
    },
    {
      "ref": "BomRef.9679682594062538.4576567344035114"
    },
    {
      "ref": "BomRef.9642927014015983.7011839252366258"
    },
    {
      "ref": "BomRef.8600948291765768.09410291332060183"
    },
    {
      "ref": "BomRef.41873196607327745.7779813290235048"
    },
    {
      "ref": "BomRef.6389616729111299.048858513373669754"
    },
    {
      "ref": "BomRef.10711624376149476.30378971532914156"
    },
    {
      "ref": "BomRef.5512700229642611.49067910431239703"
    },
    {
      "ref": "BomRef.6256210560287165.3450624851081855"
    },
    {
      "ref": "BomRef.37567027292248745.07581268429359755"
    },
    {
      "ref": "BomRef.5915165309850273.2542605602452721"
    },
    {
      "ref": "BomRef.7467081247267268.7978240810192762"
    },
    {
      "ref": "BomRef.61182297178703.6175824292461738"
    },
    {
      "ref": "BomRef.1369785486965518.28441016646890105"
    },
    {
      "ref": "BomRef.026813700702035703.5637518522889091"
    },
    {
      "ref": "BomRef.9486407515737253.8234470063246012"
    },
    {
      "ref": "BomRef.6749908958490989.4774595140502519"
    },
    {
      "ref": "BomRef.29486081123640495.8734124170706987"
    },
    {
      "ref": "BomRef.396459539093175.05943967304401554"
    },
    {
      "ref": "BomRef.1976420789654333.25486462891536177"
    },
    {
      "ref": "BomRef.638522317601062.9061123453862939"
    },
    {
      "ref": "BomRef.6700044993875508.5892838828578716"
    },
    {
      "ref": "BomRef.6494907790151351.618997674025335"
    },
    {
      "ref": "BomRef.9442058484678021.3113516388955311"
    },
    {
      "ref": "BomRef.36606419643765153.5725618659469607"
    },
    {
      "ref": "BomRef.8779491248235417.12421039780462917"
    },
    {
      "ref": "BomRef.3277733071009875.09831557579473871"
    },
    {
      "ref": "BomRef.3376297711206493.1957851498290788"
    },
    {
      "ref": "BomRef.3871849964276247.4893449023643319"
    },
    {
      "ref": "BomRef.8226533638830004.4189804940221108"
    },
    {
      "ref": "BomRef.583307849103899.6550171492927704"
    },
    {
      "ref": "BomRef.5928707323052028.14484117131808416"
    },
    {
      "ref": "BomRef.13336875914912116.09440956437812198"
    },
    {
      "ref": "BomRef.17657866979526682.9814649883423175"
    },
    {
      "ref": "BomRef.09420498196233162.8372224100157705"
    },
    {
      "ref": "BomRef.7681775543718559.16393058002058447"
    },
    {
      "ref": "BomRef.9078323994449894.9296705447335185"
    },
    {
      "ref": "BomRef.2037223003609957.6990553858168258"
    },
    {
      "ref": "BomRef.06152795812494294.3530021901379762"
    },
    {
      "ref": "BomRef.5888211273619267.970535791044228"
    },
    {
      "ref": "BomRef.18640961512670617.1278778571082515"
    },
    {
      "ref": "BomRef.5220303030806162.2083981417408195"
    },
    {
      "ref": "BomRef.8237258226930083.9508484751803226"
    },
    {
      "ref": "BomRef.7794035926772811.77583095235425"
    },
    {
      "ref": "BomRef.04429707805889771.016208775158520705"
    },
    {
      "ref": "BomRef.2726697936407906.5013737087868142"
    },
    {
      "ref": "BomRef.25984285851788336.8289933354882545"
    },
    {
      "ref": "BomRef.8932005643926842.22827573230885645"
    },
    {
      "ref": "BomRef.06620151107547723.7973386516073198"
    },
    {
      "ref": "BomRef.4448097219895859.8496550384548058"
    },
    {
      "ref": "BomRef.05342762155482039.37329605319193715"
    },
    {
      "ref": "BomRef.624618319229353.8124543178739854"
    },
    {
      "ref": "BomRef.014377694847221956.6006930728279941"
    },
    {
      "ref": "BomRef.4060751102621204.583795329942096"
    },
    {
      "ref": "BomRef.05997547558444538.12285144681881877"
    },
    {
      "ref": "BomRef.306691233650479.3184914108745118"
    },
    {
      "ref": "BomRef.2117211778482564.31115486813573534"
    },
    {
      "ref": "BomRef.5583486882302697.3879985401434414"
    },
    {
      "ref": "BomRef.8315727885006945.8894047277504243"
    },
    {
      "ref": "BomRef.9409551159293361.5854893937209357"
    },
    {
      "ref": "BomRef.9014272690494917.3168207067986012"
    },
    {
      "ref": "BomRef.7265301443260351.4370412309715802"
    },
    {
      "ref": "BomRef.12602792004093677.13898237844089922"
    },
    {
      "ref": "BomRef.9075719711185306.8652368580555755"
    },
    {
      "ref": "BomRef.15769407493695542.7697437391105496"
    },
    {
      "ref": "BomRef.6957230658729368.8357890071924468"
    },
    {
      "ref": "BomRef.5803383305596549.48501789767915104"
    },
    {
      "ref": "BomRef.2101839051176141.9249530084755786"
    },
    {
      "ref": "BomRef.9725208628706689.9720108073682088"
    },
    {
      "ref": "BomRef.25673703221047217.8949899207239959"
    },
    {
      "ref": "BomRef.6590625508715043.7509071665219865"
    },
    {
      "ref": "BomRef.5658740971019609.21739203843175525"
    },
    {
      "ref": "BomRef.44402926400307063.9214996031621715"
    },
    {
      "ref": "BomRef.4010341759440781.35080000683900747"
    },
    {
      "ref": "BomRef.3434052942822833.5397039381170327"
    },
    {
      "ref": "BomRef.33283971263764855.5367614665652368"
    },
    {
      "ref": "BomRef.2068886767530287.18576227641838572"
    },
    {
      "ref": "BomRef.5456486970552139.07243489245606194"
    },
    {
      "ref": "BomRef.22578044736389835.6700805018025822"
    },
    {
      "ref": "BomRef.6193300504397293.8720493839303153"
    },
    {
      "ref": "BomRef.675441776271153.011605783395340574"
    },
    {
      "ref": "BomRef.8523739831321816.6836741628680265"
    },
    {
      "ref": "BomRef.4161631654803263.29825156809142883"
    },
    {
      "ref": "BomRef.8085710535094197.5466021986175128"
    },
    {
      "ref": "BomRef.6411839628598913.5444423575645535"
    },
    {
      "ref": "BomRef.22980697545990802.41712410354821017"
    },
    {
      "ref": "BomRef.43967728134055784.14650436534685318"
    },
    {
      "ref": "BomRef.50751510255799.7625896369807257"
    },
    {
      "ref": "BomRef.35664584826334045.6910816968511829"
    },
    {
      "ref": "BomRef.1584853772767587.2639328553311199"
    },
    {
      "ref": "BomRef.4595584639544802.9904820822208436"
    },
    {
      "ref": "BomRef.18337437700980785.7548085589791259"
    },
    {
      "ref": "BomRef.4895747623805745.028093013759035723"
    },
    {
      "ref": "BomRef.7462134380267184.8633571336649027"
    },
    {
      "ref": "BomRef.06350124807521984.789584264917086"
    },
    {
      "ref": "BomRef.741369701796967.8024497457299178"
    },
    {
      "ref": "BomRef.8356017327909376.6803241166279047"
    },
    {
      "ref": "BomRef.9505408335772655.24691552266085004"
    },
    {
      "ref": "BomRef.20141590629089534.8561055338559156"
    },
    {
      "ref": "BomRef.8207235311155777.8406082287804161"
    },
    {
      "ref": "BomRef.692861547795587.9359387350244609"
    },
    {
      "ref": "BomRef.3885142529558141.7687475348635976"
    },
    {
      "ref": "BomRef.248725237297323.034596145334793604"
    },
    {
      "ref": "BomRef.7877324857815516.31843835605556436"
    },
    {
      "ref": "BomRef.29042988215637777.9469224760131464"
    },
    {
      "ref": "BomRef.04806015559114185.8129755548264647"
    },
    {
      "ref": "BomRef.16132078460116073.5887932322723473"
    },
    {
      "ref": "BomRef.09951863787762782.4208514726929774"
    },
    {
      "ref": "BomRef.8321758074155976.22215579648293882"
    },
    {
      "ref": "BomRef.5312832201840979.22563344220106119"
    },
    {
      "ref": "BomRef.6666388659586958.6253996220042775"
    },
    {
      "ref": "BomRef.8972279932670203.8215087135611291"
    },
    {
      "ref": "BomRef.5496756500684283.6776621350400049"
    },
    {
      "ref": "BomRef.088437751651807.6453192725102423"
    },
    {
      "ref": "BomRef.11875097979392712.5020150830897288"
    },
    {
      "ref": "BomRef.058780144264163114.18604916805807525"
    },
    {
      "ref": "BomRef.8600934580652352.7275699295992998"
    },
    {
      "ref": "pkg:oci/python@3.9.5-slim-buster?digest=sha256:9828573e6a0b02b6d0ff0bae0716b027aa21cf8e59ac18a76724d216bab7ef04",
      "dependsOn": [
        "BomRef.222876397243708.9027075281271735",
        "BomRef.3935203661690767.008572202136490348",
        "BomRef.9390377813408393.6257444931680743",
        "BomRef.3980472737203915.6651743917413009",
        "BomRef.026813700702035703.5637518522889091",
        "BomRef.5387680828856152.6388385686537119",
        "BomRef.22383416390356636.5631032528394329",
        "BomRef.29486081123640495.8734124170706987",
        "BomRef.5507000523602356.17989846013187527",
        "BomRef.9906411226171477.7059222856741965",
        "BomRef.06416709962005096.4888970081660051",
        "BomRef.8600948291765768.09410291332060183",
        "BomRef.19532797666570256.9508458421329402",
        "BomRef.11645890342214582.9519048146160358",
        "BomRef.5512700229642611.49067910431239703",
        "BomRef.5717771222802057.2843713902479015",
        "BomRef.22160974381192233.95078512074112",
        "BomRef.9806212688129069.7401904180658876",
        "BomRef.8278158252697938.1525089175639801",
        "BomRef.0031990986119523335.13419301659285665",
        "BomRef.9708420420437847.39566352630348745",
        "BomRef.20004265412418543.14515752786210412",
        "BomRef.396459539093175.05943967304401554",
        "BomRef.8724476333438951.5957306897205458",
        "BomRef.8971866655370766.6767660145496808",
        "BomRef.6417393249903256.18941865886318765",
        "BomRef.15085771322295782.8436751606754916",
        "BomRef.09529621393739218.7696974211565076",
        "BomRef.349679833039911.4594572055190672",
        "BomRef.0874616762963647.42994942210858644",
        "BomRef.41873196607327745.7779813290235048",
        "BomRef.9404764452674748.466210018422351",
        "BomRef.032198773959995486.8989407618545395",
        "BomRef.18214832576681317.7070043038742426",
        "BomRef.0095309809089823.5072495081008317",
        "BomRef.8717348879909673.13562669835811614",
        "BomRef.14451475064491726.34523007342203793",
        "BomRef.04873405550707588.5146986046532009",
        "BomRef.012535361945590129.9122748973520791",
        "BomRef.751515612825079.651987136690016",
        "BomRef.5531971328695336.8132835120680112",
        "BomRef.6227516847696897.34184629283261014",
        "BomRef.6256210560287165.3450624851081855",
        "BomRef.6251930966846826.25512310681413275",
        "BomRef.6389616729111299.048858513373669754",
        "BomRef.7484559196627131.3643589839021296",
        "BomRef.37567027292248745.07581268429359755",
        "BomRef.28913774963615935.3175846434973876",
        "BomRef.040123132165701736.8070528428543325",
        "BomRef.4362608078426272.7715125331972799",
        "BomRef.3348688085990237.3839060809638948",
        "BomRef.5104747997287611.18798433681584203",
        "BomRef.708455655678697.5211974773023408",
        "BomRef.7863311014160747.1676416986153968",
        "BomRef.4714792369182019.1162266721849895",
        "BomRef.7323940112021076.19460701179761497",
        "BomRef.2749070365904026.13946846464047624",
        "BomRef.8420249951333507.45021286727235166",
        "BomRef.9486407515737253.8234470063246012",
        "BomRef.9642927014015983.7011839252366258",
        "BomRef.7467081247267268.7978240810192762",
        "BomRef.949577046776123.3870562633565051",
        "BomRef.14147180061391673.8962006856993706",
        "BomRef.3156146626796813.6284868379111672",
        "BomRef.081780575936241.532895358768341",
        "BomRef.10186921736217669.8758035825460015",
        "BomRef.44959855469721843.9908295921008714",
        "BomRef.5915165309850273.2542605602452721",
        "BomRef.8927768714316229.19303063943966947",
        "BomRef.5627778898350738.61190172072563",
        "BomRef.23377253184068147.27898549050942245",
        "BomRef.9679682594062538.4576567344035114",
        "BomRef.6749908958490989.4774595140502519",
        "BomRef.5208843213527907.393955509910922",
        "BomRef.8251538260144693.40855689882664714",
        "BomRef.9141330146957267.10393444987624467",
        "BomRef.7408051170405284.7916020144210236",
        "BomRef.1369785486965518.28441016646890105",
        "BomRef.1976420789654333.25486462891536177",
        "BomRef.08459043109156994.9376935757832566",
        "BomRef.9324019542728219.3804584541406033",
        "BomRef.22387850531904407.8687980489040354",
        "BomRef.10711624376149476.30378971532914156",
        "BomRef.2474886628520887.9444601956018153",
        "BomRef.12215021548904725.07399066514210295",
        "BomRef.42945543822967414.48162972174599994",
        "BomRef.7366352057467452.7322840389013792",
        "BomRef.2844614411670586.669310291046318",
        "BomRef.8554812557254269.8811462143957093",
        "BomRef.7081291679447421.6095609737199661",
        "BomRef.750698910333849.6128134415094723",
        "BomRef.9900452577318635.8204726322689062",
        "BomRef.4168815025116518.6817333439662973",
        "BomRef.39399536755445586.9034341664356975",
        "BomRef.44922926910712924.8555338650751567",
        "BomRef.9261053826445684.5120762659737454",
        "BomRef.61182297178703.6175824292461738",
        "BomRef.7607252862441551.8563549855483767"
      ]
    }
  ],
  "serialNumber": "urn:uuid:bbba0619-ce6c-4595-a729-40c9008be4a1"
}